{"id": "AHO", "nodes": [{"id": "VTI V0412", "type": "primary", "x": 403645.70437539875, "y": 7153007.8660309315}, {"id": "AHO 452 $6", "type": "secondary", "x": 404470.9555862065, "y": 7158856.716948203}, {"id": "AHO V0462", "type": "primary", "x": 404481.04291444237, "y": 7158982.12511437}, {"id": "AHO 452 $3", "type": "secondary", "x": 404335.39990341867, "y": 7157884.949743786}, {"id": "TJA V0525", "type": "primary", "x": 405396.4187019663, "y": 7165524.003543383}, {"id": "AHO 452 $5", "type": "secondary", "x": 404465.3571568233, "y": 7158806.018308161}, {"id": "AHO V0461", "type": "primary", "x": 404309.30888128997, "y": 7157754.345378498}, {"id": "AHO 452 $4", "type": "secondary", "x": 404346.24483546143, "y": 7157953.54865159}], "edges": [{"n0": "AHO V0461", "n1": "VTI V0412"}, {"n0": "VTI V0412", "n1": "AHO V0461"}, {"n0": "AHO V0461", "n1": "AHO V0462"}, {"n0": "AHO V0462", "n1": "AHO V0461"}, {"n0": "AHO V0461", "n1": "AHO 452 $3"}, {"n0": "AHO 452 $3", "n1": "AHO V0461"}, {"n0": "AHO 452 $3", "n1": "AHO 452 $4"}, {"n0": "AHO 452 $4", "n1": "AHO 452 $3"}, {"n0": "AHO 452 $4", "n1": "AHO 452 $5"}, {"n0": "AHO 452 $5", "n1": "AHO 452 $4"}, {"n0": "AHO 452 $5", "n1": "AHO 452 $6"}, {"n0": "AHO 452 $6", "n1": "AHO 452 $5"}, {"n0": "AHO 452 $6", "n1": "AHO V0462"}, {"n0": "AHO V0462", "n1": "AHO 452 $6"}, {"n0": "AHO V0462", "n1": "TJA V0525"}, {"n0": "TJA V0525", "n1": "AHO V0462"}]}