{"id": "ST\u00d6", "nodes": [{"id": "ST\u00d6 V0313", "type": "primary", "x": 305979.67444434547, "y": 6861258.334129293}, {"id": "ST\u00d6 Puskin|V0313", "type": "primary", "x": 306000.33105392713, "y": 6861191.074429484}, {"id": "003 LLH-PLU $92", "type": "secondary", "x": 309074.9782122143, "y": 6852304.210941481}, {"id": "003 LLH-PLU $93", "type": "secondary", "x": 309029.50116192875, "y": 6852395.5090842405}, {"id": "KRR V0262", "type": "primary", "x": 309171.7834712778, "y": 6852128.386682599}, {"id": "003 LLH-PLU $94", "type": "secondary", "x": 309000.9442453877, "y": 6852457.222472678}, {"id": "ST\u00d6 V0312", "type": "primary", "x": 305596.7451345379, "y": 6862250.517099869}, {"id": "003 LLH-PLU $95", "type": "secondary", "x": 308958.52718203515, "y": 6852556.54072103}, {"id": "ST\u00d6 301 $8", "type": "secondary", "x": 305641.7769393037, "y": 6862120.01423686}, {"id": "003 LLH-PLU $96", "type": "secondary", "x": 308929.0845313631, "y": 6852632.077980472}, {"id": "ST\u00d6 Puskin|V0314", "type": "primary", "x": 305637.59220858425, "y": 6862114.870182387}, {"id": "003 LLH-PLU $97", "type": "secondary", "x": 308901.7473802924, "y": 6852708.325092288}, {"id": "003 LLH-PLU $98", "type": "secondary", "x": 308869.14440382173, "y": 6852809.183680937}, {"id": "ST\u00d6 V0314", "type": "primary", "x": 305665.3539896774, "y": 6862058.816219665}, {"id": "003 LLH-PLU $99", "type": "secondary", "x": 308828.62341493345, "y": 6852950.48875303}, {"id": "003 LLH-PLU $109", "type": "secondary", "x": 304378.17836734187, "y": 6865348.649521939}, {"id": "003 LLH-PLU $100", "type": "secondary", "x": 307863.7134835869, "y": 6856427.302846609}, {"id": "003 LLH-PLU $101", "type": "secondary", "x": 307835.82923429017, "y": 6856523.902309631}, {"id": "ST\u00d6 301 $3", "type": "secondary", "x": 306004.1621760287, "y": 6861197.224459896}, {"id": "003 LLH-PLU $102", "type": "secondary", "x": 307802.3000493266, "y": 6856627.612703214}, {"id": "003 LLH-PLU $103", "type": "secondary", "x": 307734.96974149277, "y": 6856806.342955444}, {"id": "003 LLH-PLU $108", "type": "secondary", "x": 304433.4263617014, "y": 6865212.425721896}, {"id": "VJR V0361", "type": "primary", "x": 302419.00271736016, "y": 6869674.993675537}, {"id": "ST\u00d6 V0311", "type": "primary", "x": 306059.8996238833, "y": 6861071.181751457}], "edges": [{"n0": "ST\u00d6 Puskin|V0314", "n1": "ST\u00d6 V0314"}, {"n0": "ST\u00d6 V0314", "n1": "ST\u00d6 Puskin|V0314"}, {"n0": "ST\u00d6 V0311", "n1": "ST\u00d6 V0312"}, {"n0": "ST\u00d6 V0312", "n1": "ST\u00d6 V0311"}, {"n0": "ST\u00d6 V0311", "n1": "003 LLH-PLU $103"}, {"n0": "003 LLH-PLU $103", "n1": "ST\u00d6 V0311"}, {"n0": "003 LLH-PLU $103", "n1": "003 LLH-PLU $102"}, {"n0": "003 LLH-PLU $102", "n1": "003 LLH-PLU $103"}, {"n0": "003 LLH-PLU $102", "n1": "003 LLH-PLU $101"}, {"n0": "003 LLH-PLU $101", "n1": "003 LLH-PLU $102"}, {"n0": "003 LLH-PLU $101", "n1": "003 LLH-PLU $100"}, {"n0": "003 LLH-PLU $100", "n1": "003 LLH-PLU $101"}, {"n0": "003 LLH-PLU $100", "n1": "003 LLH-PLU $99"}, {"n0": "003 LLH-PLU $99", "n1": "003 LLH-PLU $100"}, {"n0": "003 LLH-PLU $99", "n1": "003 LLH-PLU $98"}, {"n0": "003 LLH-PLU $98", "n1": "003 LLH-PLU $99"}, {"n0": "003 LLH-PLU $98", "n1": "003 LLH-PLU $97"}, {"n0": "003 LLH-PLU $97", "n1": "003 LLH-PLU $98"}, {"n0": "003 LLH-PLU $97", "n1": "003 LLH-PLU $96"}, {"n0": "003 LLH-PLU $96", "n1": "003 LLH-PLU $97"}, {"n0": "003 LLH-PLU $96", "n1": "003 LLH-PLU $95"}, {"n0": "003 LLH-PLU $95", "n1": "003 LLH-PLU $96"}, {"n0": "003 LLH-PLU $95", "n1": "003 LLH-PLU $94"}, {"n0": "003 LLH-PLU $94", "n1": "003 LLH-PLU $95"}, {"n0": "003 LLH-PLU $94", "n1": "003 LLH-PLU $93"}, {"n0": "003 LLH-PLU $93", "n1": "003 LLH-PLU $94"}, {"n0": "003 LLH-PLU $93", "n1": "003 LLH-PLU $92"}, {"n0": "003 LLH-PLU $92", "n1": "003 LLH-PLU $93"}, {"n0": "003 LLH-PLU $92", "n1": "KRR V0262"}, {"n0": "KRR V0262", "n1": "003 LLH-PLU $92"}, {"n0": "ST\u00d6 V0311", "n1": "ST\u00d6 301 $3"}, {"n0": "ST\u00d6 301 $3", "n1": "ST\u00d6 V0311"}, {"n0": "ST\u00d6 301 $3", "n1": "ST\u00d6 V0313"}, {"n0": "ST\u00d6 V0313", "n1": "ST\u00d6 301 $3"}, {"n0": "ST\u00d6 V0313", "n1": "ST\u00d6 Puskin|V0313"}, {"n0": "ST\u00d6 Puskin|V0313", "n1": "ST\u00d6 V0313"}, {"n0": "ST\u00d6 V0313", "n1": "ST\u00d6 V0314"}, {"n0": "ST\u00d6 V0314", "n1": "ST\u00d6 V0313"}, {"n0": "ST\u00d6 V0312", "n1": "ST\u00d6 301 $8"}, {"n0": "ST\u00d6 301 $8", "n1": "ST\u00d6 V0312"}, {"n0": "ST\u00d6 301 $8", "n1": "ST\u00d6 V0314"}, {"n0": "ST\u00d6 V0314", "n1": "ST\u00d6 301 $8"}, {"n0": "ST\u00d6 V0312", "n1": "003 LLH-PLU $108"}, {"n0": "003 LLH-PLU $108", "n1": "ST\u00d6 V0312"}, {"n0": "003 LLH-PLU $108", "n1": "003 LLH-PLU $109"}, {"n0": "003 LLH-PLU $109", "n1": "003 LLH-PLU $108"}, {"n0": "003 LLH-PLU $109", "n1": "VJR V0361"}, {"n0": "VJR V0361", "n1": "003 LLH-PLU $109"}]}